teklia_yolo/__init__.py
teklia_yolo/cli.py
teklia_yolo/extract/__init__.py
teklia_yolo/extract/bbox.py
teklia_yolo/extract/classification.py
teklia_yolo/extract/utils.py
teklia_yolo-0.2.3.dist-info/licenses/LICENSE
tests/__init__.py
tests/conftest.py
tests/test_utils.py
tests/extract/test_bbox.py
tests/extract/test_classification.py
teklia_yolo-0.2.3.dist-info/METADATA
teklia_yolo-0.2.3.dist-info/WHEEL
teklia_yolo-0.2.3.dist-info/entry_points.txt
teklia_yolo-0.2.3.dist-info/top_level.txt
teklia_yolo-0.2.3.dist-info/RECORD
