Metadata-Version: 2.4
Name: teklia-yolo
Version: 0.2.3
Summary: Scripts to train and evaluate YOLOv8 models
Author-email: Teklia <contact@teklia.com>
Maintainer-email: Teklia <contact@teklia.com>
License:                     GNU AFFERO GENERAL PUBLIC LICENSE
Keywords: python
Classifier: Programming Language :: Python :: 3 :: Only
Classifier: Programming Language :: Python :: 3.10
Classifier: Programming Language :: Python :: 3.11
Requires-Python: >=3.10
License-File: LICENSE
Requires-Dist: arkindex-export==0.1.12
Requires-Dist: more-itertools==10.1.0
Requires-Dist: opencv-python==4.10.0.84
Requires-Dist: Pillow==11.3.0
Requires-Dist: pyyaml==6.0.2
Requires-Dist: requests~=2.28
Requires-Dist: shapely==2.0.6
Requires-Dist: tenacity~=9.1
Requires-Dist: tqdm==4.66.1
Provides-Extra: docs
Requires-Dist: black==23.7.0; extra == "docs"
Requires-Dist: doc8==1.1.1; extra == "docs"
Requires-Dist: mkdocs==1.5.2; extra == "docs"
Requires-Dist: mkdocs-material==9.1.21; extra == "docs"
Requires-Dist: mkdocstrings==0.22.0; extra == "docs"
Requires-Dist: mkdocstrings-python==1.3.0; extra == "docs"
Requires-Dist: recommonmark==0.7.1; extra == "docs"
Dynamic: license-file
